<TextureAtlas imagePath="txjs75.png">
  <SubTexture name="元件 40000" x="0" y="0" width="238" height="274" hitPoint=""/>
  <SubTexture name="元件 40001" x="238" y="0" width="238" height="274"/>
  <SubTexture name="元件 40002" x="476" y="0" width="238" height="274"/>
  <SubTexture name="元件 40003" x="714" y="0" width="238" height="274"/>
  <SubTexture name="元件 40004" x="0" y="274" width="238" height="274"/>
  <SubTexture name="元件 40005" x="238" y="274" width="238" height="274"/>
  <SubTexture name="元件 40006" x="476" y="274" width="238" height="274"/>
  <SubTexture name="元件 40007" x="714" y="274" width="238" height="274"/>
</TextureAtlas>